pystratum_mysql/MySqlConnector.py
pystratum_mysql/MySqlDataLayer.py
pystratum_mysql/MySqlDefaultConnector.py
pystratum_mysql/MySqlMetadataDataLayer.py
pystratum_mysql/__init__.py
pystratum_mysql/backend/MySqlBackend.py
pystratum_mysql/backend/MySqlConstantWorker.py
pystratum_mysql/backend/MySqlRoutineLoaderWorker.py
pystratum_mysql/backend/MySqlRoutineWrapperGeneratorWorker.py
pystratum_mysql/backend/MySqlWorker.py
pystratum_mysql/backend/__init__.py
pystratum_mysql/loader/MySqlRoutineLoader.py
pystratum_mysql/loader/__init__.py
pystratum_mysql/loader/helper/MySqlDataTypeHelper.py
pystratum_mysql/loader/helper/__init__.py
pystratum_mysql/wrapper/MySqlBulkWrapper.py
pystratum_mysql/wrapper/MySqlFunctionsWrapper.py
pystratum_mysql/wrapper/MySqlInsertManyWrapper.py
pystratum_mysql/wrapper/MySqlLogWrapper.py
pystratum_mysql/wrapper/MySqlMultiWrapper.py
pystratum_mysql/wrapper/MySqlNoneWrapper.py
pystratum_mysql/wrapper/MySqlRow0Wrapper.py
pystratum_mysql/wrapper/MySqlRow1Wrapper.py
pystratum_mysql/wrapper/MySqlRowsWithIndexWrapper.py
pystratum_mysql/wrapper/MySqlRowsWithKeyWrapper.py
pystratum_mysql/wrapper/MySqlRowsWrapper.py
pystratum_mysql/wrapper/MySqlSingleton0Wrapper.py
pystratum_mysql/wrapper/MySqlSingleton1Wrapper.py
pystratum_mysql/wrapper/MySqlTableWrapper.py
pystratum_mysql/wrapper/MySqlWrapper.py
pystratum_mysql/wrapper/__init__.py
pystratum_mysql-3.0.0.dist-info/LICENSE.md
pystratum_mysql-3.0.0.dist-info/METADATA
pystratum_mysql-3.0.0.dist-info/WHEEL
pystratum_mysql-3.0.0.dist-info/RECORD
