Metadata-Version: 2.1
Name: PyStratum-MySQL
Version: 3.0.0
Summary: PyStratum MySQL: MySQL & MariaDB Backend
Home-page: https://github.com/DatabaseStratum/py-stratum-mysql
License: MIT
Keywords: PyStratum,MySQL,MariaDB
Author: Set Based IT Consultancy
Author-email: info@setbased.nl
Requires-Python: >=3.12.0,<4.0.0
Classifier: Development Status :: 5 - Production/Stable
Classifier: Intended Audience :: Developers
Classifier: License :: OSI Approved :: MIT License
Classifier: Programming Language :: Python :: 3
Classifier: Programming Language :: Python :: 3.12
Classifier: Topic :: Software Development :: Build Tools
Classifier: Topic :: Software Development :: Code Generators
Classifier: Topic :: System :: Installation/Setup
Requires-Dist: PyStratum-Backend (>=2.1.0,<3.0.0)
Requires-Dist: PyStratum-Common (>=3.0.3,<4.0.0)
Requires-Dist: PyStratum-Middle (>=1.2.0,<2.0.0)
Requires-Dist: mysql-connector-python (>=9.0.0,<10.0.0)
Project-URL: Documentation, https://stratum.readthedocs.io/
Project-URL: Repository, https://github.com/DatabaseStratum/py-stratum-mysql
